crosstrainer/__init__.py
crosstrainer/crosstrainer.py
crosstrainer-0.1.5.dist-info/LICENSE
crosstrainer-0.1.5.dist-info/METADATA
crosstrainer-0.1.5.dist-info/WHEEL
crosstrainer-0.1.5.dist-info/top_level.txt
crosstrainer-0.1.5.dist-info/RECORD
